servicecatalog_puppet/__init__.py
servicecatalog_puppet/asset_helpers.py
servicecatalog_puppet/asset_helpers_unit_test.py
servicecatalog_puppet/aws.py
servicecatalog_puppet/cli.py
servicecatalog_puppet/config.py
servicecatalog_puppet/config_unit_test.py
servicecatalog_puppet/constants.py
servicecatalog_puppet/core.py
servicecatalog_puppet/example-config-small.yaml
servicecatalog_puppet/macros.py
servicecatalog_puppet/manifest.yaml
servicecatalog_puppet/manifest_utils.py
servicecatalog_puppet/manifest_utils_for_launches.py
servicecatalog_puppet/manifest_utils_for_spoke_local_portfolios.py
servicecatalog_puppet/manifest_utils_unit_test.py
servicecatalog_puppet/puppet_schema_extensions.py
servicecatalog_puppet/schema.yaml
servicecatalog_puppet/sdk.py
servicecatalog_puppet/servicecatalog-puppet-initialiser.template.yaml
servicecatalog_puppet/servicecatalog-puppet-org-master.template.yaml
servicecatalog_puppet/servicecatalog-puppet-regional.template.yaml
servicecatalog_puppet/servicecatalog-puppet-spoke.template.yaml
servicecatalog_puppet/servicecatalog-puppet.template.yaml
servicecatalog_puppet/data/account-vending/all-tasks-for-launch-b.json
servicecatalog_puppet/data/account-vending/all-tasks.json
servicecatalog_puppet/data/account-vending/deployment-map.json
servicecatalog_puppet/data/account-vending/launch-a.json
servicecatalog_puppet/data/account-vending/launch-b.json
servicecatalog_puppet/data/account-vending/launch-c.json
servicecatalog_puppet/data/account-vending/launch-details-for-launch-b.json
servicecatalog_puppet/data/account-vending/manifest-tasks.json
servicecatalog_puppet/data/account-vending/manifest.json
servicecatalog_puppet/data/account-vending/manifest_with_numbers.json
servicecatalog_puppet/data/manifest_utils/test_convert_manifest_into_task_defs_handles_depends_on_without-leaks.yaml
servicecatalog_puppet/data/manifest_utils/test_convert_manifest_into_task_defs_handles_depends_on_without-leaks_expected.yaml
aws_service_catalog_puppet-0.77.0.dist-info/LICENSE
aws_service_catalog_puppet-0.77.0.dist-info/METADATA
aws_service_catalog_puppet-0.77.0.dist-info/NOTICE
aws_service_catalog_puppet-0.77.0.dist-info/WHEEL
aws_service_catalog_puppet-0.77.0.dist-info/entry_points.txt
aws_service_catalog_puppet-0.77.0.dist-info/top_level.txt
aws_service_catalog_puppet-0.77.0.dist-info/RECORD
