Metadata-Version: 2.1
Name: aws-service-catalog-puppet
Version: 0.77.0
Summary: Making it easier to deploy ServiceCatalog products
Home-page: https://github.com/awslabs/aws-service-catalog-puppet-framework
Author: Eamonn Faherty
Author-email: aws-service-catalog-tools@amazon.com
License: UNKNOWN
Platform: UNKNOWN
Classifier: Development Status :: 5 - Production/Stable
Classifier: Intended Audience :: Developers
Classifier: Programming Language :: Python :: 3
Classifier: License :: OSI Approved :: Apache Software License
Classifier: Operating System :: OS Independent
Classifier: Natural Language :: English
Requires-Dist: better-boto (==0.28.0)
Requires-Dist: boto3 (==1.14.14)
Requires-Dist: botocore (==1.17.14)
Requires-Dist: certifi (==2020.6.20)
Requires-Dist: cfn-flip (==1.2.1)
Requires-Dist: chardet (==3.0.4)
Requires-Dist: click (==7.0)
Requires-Dist: colorclass (==2.2.0)
Requires-Dist: docopt (==0.6.2)
Requires-Dist: docutils (==0.14)
Requires-Dist: idna (==2.8)
Requires-Dist: jinja2 (==2.10.1)
Requires-Dist: jmespath (==0.10.0)
Requires-Dist: lockfile (==0.12.2)
Requires-Dist: luigi (==2.8.9)
Requires-Dist: markupsafe (==1.1.1)
Requires-Dist: progressbar (==2.5)
Requires-Dist: psutil (==5.7.0)
Requires-Dist: pykwalify (==1.7.0)
Requires-Dist: python-daemon (==2.1.2)
Requires-Dist: python-dateutil (==2.8.1)
Requires-Dist: pyyaml (==5.1)
Requires-Dist: requests (==2.22.0)
Requires-Dist: s3transfer (==0.3.3)
Requires-Dist: six (==1.15.0)
Requires-Dist: terminaltables (==3.1.0)
Requires-Dist: tornado (==5.1.1)
Requires-Dist: urllib3 (==1.25.9) ; python_version != "3.4"
